
{ 
  "projects" : [
    {
      "id": "campsim",
      "title": "camping simulator 2020",
      "subtitle": "a conversation on August 28",
      "link": "https://frojo.itch.io/camping",
      "date": "2020-09",
      "documentation": false
    },
    {
      "id": "bloomfield",
      "title": "a summer afternoon in bloomfield",
      "subtitle": "a love letter to the neighborhood",
      "link": "https://frojo.itch.io/a-summer-afternoon-in-bloomfield",
      "date": "2019-10",
      "documentation": false
    },
    {
      "id": "loops",
      "title": "loops",
      "subtitle": "a rumination on habit",
      "link": "https://frojo.itch.io/loops",
      "date": "2020-06",
      "documentation": false
    },
    {
      "id": "souls",
      "title": "sou.ls",
      "subtitle": "a lonely social network",
      "date": "2020-08",
      "documentation": true
    },
    {
      "id": "july4",
      "title": "july4",
      "subtitle": "a moment on a rooftop",
      "link": "https://frojo.itch.io/july4",
      "date": "2020-07",
      "documentation": false
    },
    {
      "id": "godot-workshop",
      "title": "Godot Workshop (Babycastles Academy)",
      "subtitle": "intro to open-source game engine",
      "date": "2020-05",
      "documentation": true
    },
    {
      "id": "word-garden",
      "title": "word garden",
      "subtitle": "a garden of words",
      "date": "2020-03",
      "documentation": true
    },
    {
      "id": "pico8-pcd2020",
      "title": "Intro. to PICO-8 (Processing Community Day)",
      "subtitle": "the joy of working with limitations",
      "date": "2020-02",
      "documentation": true
    },
    {
      "id": "pride-prejudice-pussy",
      "title": "Pride and Prejudice and Pussy",
      "subtitle": "surrealist erotica",
      "date": "2020-03",
      "documentation": true
    },
    {
      "id": "what-do-you-wish",
      "title": "what do you wish you could say?",
      "subtitle": "a respite",
      "date": "2019-12",
      "documentation": true
    },
    {
      "id": "sail",
      "title": "sail.p8",
      "subtitle": "two-player sailing game in pico8",
      "link": "https://www.lexaloffle.com/bbs/?tid=33712",
      "date": "2019-03",
      "documentation": false
    }
  ]
}
